kili_formats/__init__.py
kili_formats/exceptions.py
kili_formats/kili.py
kili_formats/types.py
kili_formats/format/llm.py
kili_formats/format/voc.py
kili_formats/format/yolo.py
kili_formats/format/coco/__init__.py
kili_formats/format/coco/types.py
kili_formats/format/geojson/__init__.py
kili_formats/format/geojson/bbox.py
kili_formats/format/geojson/classification.py
kili_formats/format/geojson/collection.py
kili_formats/format/geojson/exceptions.py
kili_formats/format/geojson/geometrycollection.py
kili_formats/format/geojson/line.py
kili_formats/format/geojson/multilinestring.py
kili_formats/format/geojson/multipoint.py
kili_formats/format/geojson/point.py
kili_formats/format/geojson/polygon.py
kili_formats/format/geojson/segmentation.py
kili_formats/format/geojson/transcription.py
kili_formats/media/common.py
kili_formats/media/image.py
kili_formats/media/video.py
kili_formats/tool/annotations_to_json_response.py
kili_formats/tool/base.py
kili_formats/tool/pdf.py
kili_formats/tool/video.py
kili_formats-1.1.0.dist-info/licenses/LICENSE.txt
kili_formats-1.1.0.dist-info/METADATA
kili_formats-1.1.0.dist-info/WHEEL
kili_formats-1.1.0.dist-info/top_level.txt
kili_formats-1.1.0.dist-info/RECORD
