Metadata-Version: 2.4
Name: kili-formats
Version: 1.1.0
Author-email: Kili Technology <contact@kili-technology.com>
License: 
Requires-Python: >=3.10
License-File: LICENSE.txt
Requires-Dist: typing-extensions<5.0.0,>=4.1.0
Provides-Extra: all
Requires-Dist: numpy<3,>=2; extra == "all"
Requires-Dist: shapely<3,>=1.8; extra == "all"
Requires-Dist: Pillow<13.0.0,>=9.0.0; extra == "all"
Requires-Dist: ffmpeg-python<0.3.0,>=0.2.0; extra == "all"
Provides-Extra: dev
Requires-Dist: pytest; extra == "dev"
Requires-Dist: requests<3.0.0,>=2.0.0; extra == "dev"
Requires-Dist: pre-commit<4.0.0,>=3.3.0; extra == "dev"
Requires-Dist: pylint==3.0.3; extra == "dev"
Requires-Dist: pyright==1.1.347; extra == "dev"
Requires-Dist: shapely<3,>=1.8; extra == "dev"
Requires-Dist: Pillow<13.0.0,>=9.0.0; extra == "dev"
Requires-Dist: ffmpeg-python<0.3.0,>=0.2.0; extra == "dev"
Provides-Extra: coco
Requires-Dist: numpy<3,>=2; extra == "coco"
Requires-Dist: shapely<3,>=1.8; extra == "coco"
Provides-Extra: image
Requires-Dist: Pillow<13.0.0,>=9.0.0; extra == "image"
Provides-Extra: video
Requires-Dist: ffmpeg-python<0.3.0,>=0.2.0; extra == "video"
Dynamic: license-file
